processes/__init__.py
processes/html_logging.py
processes/process.py
processes/task.py
processes-1.0.5.dist-info/METADATA
processes-1.0.5.dist-info/WHEEL
processes-1.0.5.dist-info/licenses/LICENSE
processes-1.0.5.dist-info/RECORD
