Metadata-Version: 2.4
Name: processes
Version: 1.0.5
Summary: A Python library for managing and executing dependent tasks in parallel or sequential order with automatic dependency resolution and topological sorting
Project-URL: Homepage, https://github.com/oliverm91/processes
Project-URL: Documentation, https://oliverm91.github.io/processes/
Project-URL: Repository, https://github.com/oliverm91/processes
Project-URL: Issues, https://github.com/oliverm91/processes/issues
Project-URL: Changelog, https://github.com/oliverm91/processes/blob/main/CHANGELOG.md
Author-email: Oliver Mohr Bonometti <oliver.mohr.b@gmail.com>
License-Expression: MIT
License-File: LICENSE
Keywords: dag,dependencies,etl,parallel,process,tasks,topological-sort,workflow
Classifier: Development Status :: 4 - Beta
Classifier: Intended Audience :: Developers
Classifier: Programming Language :: Python :: 3
Classifier: Programming Language :: Python :: 3.10
Classifier: Programming Language :: Python :: 3.11
Classifier: Programming Language :: Python :: 3.12
Classifier: Programming Language :: Python :: 3.13
Classifier: Programming Language :: Python :: 3.14
Requires-Python: >=3.10
